{
	"description": "项目配置文件。",
	"setting": {
		"urlCheck": true,
		"es6": true,
		"postcss": true,
		"minified": true,
		"newFeature": true
	},
	"compileType": "miniprogram",
	"libVersion": "1.6.0",
	"appid": "wxdf2eba3b79b83110",
	"projectname": "%E5%BE%AE%E5%A4%A9%E4%BD%BF",
	"condition": {
		"search": {
			"current": -1,
			"list": []
		},
		"conversation": {
			"current": -1,
			"list": []
		},
		"miniprogram": {
			"current": 25,
			"list": [
				{
					"id": 2,
					"name": "验证码",
					"pathName": "pages/register/personInfo/personInfo",
					"query": ""
				},
				{
					"id": -1,
					"name": "browseMe",
					"pathName": "pages/message/browseMe/browseMe",
					"query": ""
				},
				{
					"id": 5,
					"name": "分享后的我的项目 ",
					"pathName": "pages/projectDetail/projectDetail",
					"query": "id=e0qQB10v&&share_id=mr93M3KW"
				},
				{
					"id": 5,
					"name": "project_orgMatch",
					"pathName": "pages/organization/subPage/project_orgMatch/project_orgMatch",
					"query": "project_id=a1ryoGW3"
				},
				{
					"id": -1,
					"name": "org_search",
					"pathName": "pages/organization/org_search/org_search",
					"query": ""
				},
				{
					"id": 6,
					"name": "编辑项目",
					"pathName": "pages/myProject/publishProject/publishProject",
					"query": "pro_id=QWNn9gW1"
				},
				{
					"id": 13,
					"name": "投资案例",
					"pathName": "pages/organization/subPage/list_investCase/list_investCase",
					"query": "investment_id=1080"
				},
				{
					"id": 14,
					"name": "项目评价",
					"pathName": "pages/projectScale/projectEvaluation/projectEvaluation",
					"query": ""
				},
				{
					"id": 17,
					"name": "创建项目",
					"pathName": "pages/myProject/publishProject/publishProject",
					"query": ""
				},
				{
					"id": 18,
					"name": "投资需求",
					"pathName": "pages/match/match/investDemand/investDemand",
					"query": "current=1"
				},
				{
					"id": 19,
					"name": "领域表单",
					"pathName": "pages/form/industry/industry",
					"query": ""
				},
				{
					"id": 20,
					"name": "认证资料",
					"pathName": "pages/my/identity/identityEdit/identityEdit",
					"query": "group_id=18&authenticate_id=7899&isUpdate=0"
				},
				{
					"id": -1,
					"name": "成功案例",
					"pathName": "pages/my/investCaseEdit/investCaseEdit",
					"query": "index=0&case_id=415"
				},
				{
					"id": -1,
					"name": "我的投资名片",
					"pathName": "pages/my/myNew/myNew",
					"query": ""
				},
				{
					"id": 22,
					"name": "项目推送",
					"pathName": "pages/message/pushProject/pushProject",
					"query": "type=7&num=1"
				},
				{
					"id": 18,
					"name": "项目详情",
					"pathName": "pages/projectDetail/projectDetail",
					"query": "id=QWNn5OW1&index=0"
				},
				{
					"id": 17,
					"name": "项目店铺",
					"pathName": "pages/my/projectShop/projectShop/projectShop",
					"query": ""
				},
				{
					"id": 22,
					"name": "项目推送",
					"pathName": "pages/message/pushProject/pushProject",
					"query": "type=7&num=1"
				},
				{
					"id": -1,
					"name": "浏览项目的人",
					"pathName": "pages/message/viewProjectUser/viewProjectUser",
					"query": "project_id=PpPk2ZWR"
				},
				{
					"id": 22,
					"name": "约谈",
					"pathName": "pages/message/contactProject/projectList/projectList",
					"query": "id=xpE8b5Wq"
				},
				{
					"id": -1,
					"name": "找项目投资人",
					"pathName": "pages/matchInvestor/matchInvestor",
					"query": ""
				},
				{
					"id": -1,
					"name": "案例添加",
					"pathName": "pages/my/investCaseEdit/investCaseEdit",
					"query": ""
				},
				{
					"id": -1,
					"name": "编辑案例添加",
					"pathName": "pages/my/investCaseEdit/investCaseEdit",
					"query": "index=2&case_id=481"
				},
				{
					"id": -1,
					"name": "找投资人",
					"pathName": "pages/matchInvestor/matchInvestor",
					"query": ""
				},
				{
					"id": -1,
					"name": "项目店铺筛选",
					"pathName": "pages/my/projectShop/tagFilter/tagFilter",
					"query": ""
				},
				{
					"id": 25,
					"name": "裁剪",
					"pathName": "pages/register/bindSuccess/bindSuccess",
					"query": ""
				}
			]
		}
	}
}